venus/__init__.py
venus/__main__.py
venus/_decorator_utils.py
venus/_module_utils.py
venus/agent.py
venus/caching.py
venus/constants.py
venus/decorators.py
venus/errors.py
venus/logger.py
venus/mcp_server.py
venus/mock_types.py
venus/permissions.py
venus/prompts.py
venus/py.typed
venus/schemas.py
venus/settings.py
venus/types.py
venus/helpers/__init__.py
venus/helpers/e2b.py
venus/helpers/io.py
venus/helpers/sandbox/__init__.py
venus/helpers/sandbox/_client.py
venus/helpers/sandbox/e2b.py
venus/models/__init__.py
venus/models/openai.py
venai-1.29.2.dist-info/METADATA
venai-1.29.2.dist-info/WHEEL
venai-1.29.2.dist-info/entry_points.txt
venai-1.29.2.dist-info/licenses/LICENSE
venai-1.29.2.dist-info/RECORD
