Metadata-Version: 2.4
Name: venai
Version: 1.29.2
Summary: VenusAI is a secure and extensible Agent framework built for modern AI applications.
Project-URL: Documentation, https://venai.tech/docs
Project-URL: Source, https://github.com/VenusAgent/VenusAI
Project-URL: Tracker, https://github.com/VenusAgent/VenusAI/issues
Author-email: Mert Sirakaya <contact@tomris.dev>
Maintainer-email: Mert Sirakaya <contact@tomris.dev>
License: MIT
License-File: LICENSE
Keywords: agent,agentic ai,ai,ai agent,llm,pydantic,pydantic-ai,safety,sandbox,self-healing
Classifier: License :: OSI Approved :: MIT License
Classifier: Operating System :: OS Independent
Classifier: Programming Language :: Python :: 3
Classifier: Programming Language :: Python :: 3.10
Classifier: Programming Language :: Python :: 3.11
Classifier: Programming Language :: Python :: 3.12
Requires-Python: >=3.10
Requires-Dist: aiocache
Requires-Dist: aiofiles
Requires-Dist: async-lru
Requires-Dist: cachetools
Requires-Dist: click
Requires-Dist: e2b-code-interpreter
Requires-Dist: fasta2a
Requires-Dist: fastapi
Requires-Dist: logfire
Requires-Dist: mcp
Requires-Dist: pydantic
Requires-Dist: pydantic-ai
Requires-Dist: python-dotenv
Requires-Dist: rich
Requires-Dist: tinydb
Requires-Dist: typing-extensions
Requires-Dist: uvicorn
